SOAPify/__init__.py
SOAPify/analysis.py
SOAPify/classify.py
SOAPify/cli.py
SOAPify/distances.py
SOAPify/engine.py
SOAPify/saponify.py
SOAPify/utils.py
SOAPify/HDF5er/HDF5To.py
SOAPify/HDF5er/HDF5erUtils.py
SOAPify/HDF5er/ToHDF5.py
SOAPify/HDF5er/__init__.py
SOAPify/transitions/__init__.py
SOAPify/transitions/tracker.py
cpctools-0.1.1.dist-info/METADATA
cpctools-0.1.1.dist-info/WHEEL
cpctools-0.1.1.dist-info/entry_points.txt
cpctools-0.1.1.dist-info/licenses/LICENSE
cpctools-0.1.1.dist-info/RECORD
