Metadata-Version: 2.1
Name: cpctools
Version: 0.1.1
Summary: A package for analysing molecular systems
Project-URL: Homepage, https://github.com/GMPavanLab/cpctools
Author-email: Daniele Rapetti <daniele.rapetti@polito.it>
License-Expression: MIT
License-File: LICENSE
Keywords: Molecular Dynamics,SOAP,simulation,simulation analysis
Classifier: License :: OSI Approved :: MIT License
Classifier: Operating System :: OS Independent
Classifier: Programming Language :: Python :: 3.8
Classifier: Programming Language :: Python :: 3.9
Classifier: Programming Language :: Python :: 3.10
Requires-Python: <3.11,>=3.8
Requires-Dist: ase==3.22.1
Requires-Dist: deprecated==1.2.13
Requires-Dist: h5py==3.8.0
Requires-Dist: mdanalysis==2.4.2
Requires-Dist: numpy<1.24,>=1.18
Provides-Extra: docs
Requires-Dist: docutils<0.18; extra == 'docs'
Requires-Dist: ipython; extra == 'docs'
Requires-Dist: myst-parser==0.18.1; extra == 'docs'
Requires-Dist: nbsphinx==0.9.0; extra == 'docs'
Requires-Dist: sphinx-autodoc-typehints==1.22; extra == 'docs'
Requires-Dist: sphinx-gallery==0.12.2; extra == 'docs'
Requires-Dist: sphinx-rtd-theme==1.2.0; extra == 'docs'
Requires-Dist: sphinx<6,>=4; extra == 'docs'
Provides-Extra: dscribe
Requires-Dist: dscribe<=1.2.2,>1.2.0; extra == 'dscribe'
Provides-Extra: quippy
Requires-Dist: quippy-ase==0.9.10; extra == 'quippy'
Provides-Extra: tests
Requires-Dist: coverage[toml]; extra == 'tests'
Requires-Dist: pytest; extra == 'tests'
Requires-Dist: pytest-cov; extra == 'tests'
